growthbook_openfeature_provider/__init__.py
growthbook_openfeature_provider/provider.py
growthbook_openfeature_provider-0.0.6.dist-info/METADATA
growthbook_openfeature_provider-0.0.6.dist-info/WHEEL
growthbook_openfeature_provider-0.0.6.dist-info/licenses/LICENSE
growthbook_openfeature_provider-0.0.6.dist-info/RECORD
