Metadata-Version: 2.4
Name: growthbook-openfeature-provider
Version: 0.0.6
Summary: GrowthBook provider for OpenFeature
Project-URL: Homepage, https://github.com/growthbook/growthbook-openfeature-provider-python/
Project-URL: Issues, https://github.com/growthbook/growthbook-openfeature-provider-python/issues
Author-email: GrowthBook Maintainers <hello@growthbook.io>
License: MIT License
License-File: LICENSE
Classifier: Intended Audience :: Developers
Classifier: License :: OSI Approved :: MIT License
Classifier: Operating System :: OS Independent
Classifier: Programming Language :: Python :: 3
Classifier: Programming Language :: Python :: 3.9
Classifier: Programming Language :: Python :: 3.10
Classifier: Programming Language :: Python :: 3.11
Classifier: Programming Language :: Python :: 3.12
Classifier: Topic :: Software Development :: Libraries :: Python Modules
Requires-Python: >=3.9
Requires-Dist: growthbook>=1.2.1
Requires-Dist: openfeature-sdk>=0.8.1
Provides-Extra: dev
Requires-Dist: black>=23.0.0; extra == 'dev'
Requires-Dist: isort>=5.12.0; extra == 'dev'
Requires-Dist: mypy>=1.0.0; extra == 'dev'
Requires-Dist: pytest-asyncio>=0.21.0; extra == 'dev'
Requires-Dist: pytest-cov>=4.0.0; extra == 'dev'
Requires-Dist: pytest>=7.0.0; extra == 'dev'
